rfpOperationsTest4/__init__.py
rfpOperationsTest4/database/__init__.py
rfpOperationsTest4/database/create.py
rfpOperationsTest4/database/delete.py
rfpOperationsTest4/database/funcs.py
rfpOperationsTest4/database/instance.py
rfpOperationsTest4/database/update.py
rfpOperationsTest4/identifier/__init__.py
rfpOperationsTest4/identifier/event.py
rfpOperationsTest4/identifier/hash_p_feature.py
rfpOperationsTest4/identifier/prop_identifier.py
rfpOperationsTest4/scraper/__init__.py
rfpOperationsTest4/scraper/base.py
rfpOperationsTest4/scraper/zoopla.py
rfpOperationsTest4-0.0.1.dist-info/METADATA
rfpOperationsTest4-0.0.1.dist-info/WHEEL
rfpOperationsTest4-0.0.1.dist-info/top_level.txt
rfpOperationsTest4-0.0.1.dist-info/RECORD
